backtrade/__init__.py
backtrade/backtest/__init__.py
backtrade/backtest/backtest.py
backtrade/backtest/dtypes.py
backtrade/finished_order.py
backtrade/logic.py
backtrade/order.py
backtrade/py.typed
backtrade/validator.py
backtrade-0.7.2.dist-info/LICENSE
backtrade-0.7.2.dist-info/WHEEL
backtrade-0.7.2.dist-info/METADATA
backtrade-0.7.2.dist-info/RECORD
