Metadata-Version: 2.1
Name: backtrade
Version: 0.7.2
Summary: A small Python package for backtesting.
Home-page: https://github.com/34j/backtrade
License: GNU General Public License v3
Author: 34j
Author-email: 55338215+34j@users.noreply.github.com
Requires-Python: >=3.8,<4.0
Classifier: Development Status :: 2 - Pre-Alpha
Classifier: Intended Audience :: Developers
Classifier: License :: Other/Proprietary License
Classifier: Natural Language :: English
Classifier: Operating System :: OS Independent
Classifier: Programming Language :: Python :: 3
Classifier: Programming Language :: Python :: 3.8
Classifier: Programming Language :: Python :: 3.9
Classifier: Programming Language :: Python :: 3.10
Classifier: Programming Language :: Python :: 3.11
Classifier: Topic :: Software Development :: Libraries
Requires-Dist: attrs
Requires-Dist: exceptiongroup
Requires-Dist: fitter
Requires-Dist: joblib
Requires-Dist: matplotlib
Requires-Dist: pandas
Requires-Dist: plottable
Requires-Dist: scipy
Requires-Dist: tqdm
Project-URL: Bug Tracker, https://github.com/34j/backtrade/issues
Project-URL: Changelog, https://github.com/34j/backtrade/blob/main/CHANGELOG.md
Project-URL: Documentation, https://backtrade.readthedocs.io
Project-URL: Repository, https://github.com/34j/backtrade
